econpapers/__init__.py
econpapers/journals.py
econpapers-0.1.8.dist-info/LICENSE
econpapers-0.1.8.dist-info/METADATA
econpapers-0.1.8.dist-info/WHEEL
econpapers-0.1.8.dist-info/top_level.txt
econpapers-0.1.8.dist-info/RECORD
