Metadata-Version: 2.1
Name: econpapers
Version: 0.1.8
Summary: A package to collect data about economic papers in journals.
Author-email: Matteo Tinè <matteo.tine@wiso.uni-koeln.de>
Project-URL: Homepage, https://github.com/matteo-tine/EconPapers
Classifier: Programming Language :: Python :: 3
Classifier: License :: OSI Approved :: MIT License
Classifier: Operating System :: OS Independent
Requires-Python: >=3.11
License-File: LICENSE
Requires-Dist: beautifulsoup4
Requires-Dist: click
Requires-Dist: colorama
Requires-Dist: jax
Requires-Dist: jaxlib
Requires-Dist: lxml
Requires-Dist: ml-dtypes
Requires-Dist: mypy-extensions
Requires-Dist: numpy
Requires-Dist: opt-einsum
Requires-Dist: packaging
Requires-Dist: pathspec
Requires-Dist: platformdirs
Requires-Dist: scipy
Requires-Dist: soupsieve
Requires-Dist: typing-extensions
Provides-Extra: dev
Requires-Dist: black ==25.1.0 ; extra == 'dev'
